{"trial_id": "242175663389af4e16b56d4e1ce0cdd7", "hyperparameters": {"space": [{"class_name": "Int", "config": {"name": "units_1", "default": null, "min_value": 32, "max_value": 64, "step": 8, "sampling": null}}, {"class_name": "Int", "config": {"name": "units_2", "default": null, "min_value": 32, "max_value": 64, "step": 8, "sampling": null}}, {"class_name": "Int", "config": {"name": "units_3", "default": null, "min_value": 32, "max_value": 64, "step": 8, "sampling": null}}], "values": {"units_1": 56, "units_2": 32, "units_3": 56}}, "metrics": {"metrics": {"loss": {"direction": "min", "observations": [{"value": [2.0731077194213867], "step": 0}]}, "accuracy": {"direction": "max", "observations": [{"value": [0.9671111106872559], "step": 0}]}, "val_loss": {"direction": "min", "observations": [{"value": [2.0459372997283936], "step": 0}]}, "val_accuracy": {"direction": "max", "observations": [{"value": [0.9760000109672546], "step": 0}]}, "lr": {"direction": "min", "observations": [{"value": [0.0010000000474974513], "step": 0}]}}}, "score": 0.9760000109672546, "best_step": 0, "status": "COMPLETED"}